techghoshal/__init__.py
techghoshal/hello.py
techghoshal-0.3.1.dist-info/METADATA
techghoshal-0.3.1.dist-info/WHEEL
techghoshal-0.3.1.dist-info/top_level.txt
techghoshal-0.3.1.dist-info/RECORD
