Metadata-Version: 2.1
Name: techghoshal
Version: 0.3.1
Summary: Basic Hello package
Home-page: UNKNOWN
Author: techghoshal
Author-email: techghoshal@gmail.com
License: UNKNOWN
Keywords: hello-wordl,testing
Platform: UNKNOWN
Requires-Dist: requests
